[{"id": 1, "char": "匕"}, {"id": 2, "char": "刁"}, {"id": 3, "char": "丐"}, {"id": 4, "char": "歹"}, {"id": 5, "char": "戈"}, {"id": 6, "char": "夭"}, {"id": 7, "char": "仑"}, {"id": 8, "char": "冗"}, {"id": 9, "char": "讥"}, {"id": 10, "char": "邓"}, {"id": 11, "char": "艾"}, {"id": 12, "char": "夯"}, {"id": 13, "char": "凸"}, {"id": 14, "char": "卢"}, {"id": 15, "char": "叭"}, {"id": 16, "char": "叽"}, {"id": 17, "char": "皿"}, {"id": 18, "char": "凹"}, {"id": 19, "char": "囚"}, {"id": 20, "char": "矢"}, {"id": 21, "char": "乍"}, {"id": 22, "char": "尔"}, {"id": 23, "char": "冯"}, {"id": 24, "char": "玄"}, {"id": 25, "char": "邦"}, {"id": 26, "char": "迂"}, {"id": 27, "char": "邢"}, {"id": 28, "char": "芋"}, {"id": 29, "char": "芍"}, {"id": 30, "char": "吏"}, {"id": 31, "char": "夷"}, {"id": 32, "char": "吁"}, {"id": 33, "char": "吕"}, {"id": 34, "char": "吆"}, {"id": 35, "char": "屹"}, {"id": 36, "char": "廷"}, {"id": 37, "char": "迄"}, {"id": 38, "char": "臼"}, {"id": 39, "char": "仲"}, {"id": 40, "char": "伦"}, {"id": 41, "char": "伊"}, {"id": 42, "char": "肋"}, {"id": 43, "char": "旭"}, {"id": 44, "char": "匈"}, {"id": 45, "char": "凫"}, {"id": 46, "char": "妆"}, {"id": 47, "char": "亥"}, {"id": 48, "char": "汛"}, {"id": 49, "char": "讳"}, {"id": 50, "char": "讶"}, {"id": 51, "char": "讹"}, {"id": 52, "char": "讼"}, {"id": 53, "char": "诀"}, {"id": 54, "char": "弛"}, {"id": 55, "char": "阱"}, {"id": 56, "char": "驮"}, {"id": 57, "char": "驯"}, {"id": 58, "char": "纫"}, {"id": 59, "char": "玖"}, {"id": 60, "char": "玛"}, {"id": 61, "char": "韧"}, {"id": 62, "char": "抠"}, {"id": 63, "char": "扼"}, {"id": 64, "char": "汞"}, {"id": 65, "char": "扳"}, {"id": 66, "char": "抡"}, {"id": 67, "char": "坎"}, {"id": 68, "char": "坞"}, {"id": 69, "char": "抑"}, {"id": 70, "char": "拟"}, {"id": 71, "char": "抒"}, {"id": 72, "char": "芙"}, {"id": 73, "char": "芜"}, {"id": 74, "char": "苇"}, {"id": 75, "char": "芥"}, {"id": 76, "char": "芯"}, {"id": 77, "char": "芭"}, {"id": 78, "char": "杖"}, {"id": 79, "char": "杉"}, {"id": 80, "char": "巫"}, {"id": 81, "char": "杈"}, {"id": 82, "char": "甫"}, {"id": 83, "char": "匣"}, {"id": 84, "char": "轩"}, {"id": 85, "char": "卤"}, {"id": 86, "char": "肖"}, {"id": 87, "char": "吱"}, {"id": 88, "char": "吠"}, {"id": 89, "char": "呕"}, {"id": 90, "char": "呐"}, {"id": 91, "char": "吟"}, {"id": 92, "char": "呛"}, {"id": 93, "char": "吻"}, {"id": 94, "char": "吭"}, {"id": 95, "char": "邑"}, {"id": 96, "char": "囤"}, {"id": 97, "char": "吮"}, {"id": 98, "char": "岖"}, {"id": 99, "char": "牡"}, {"id": 100, "char": "佑"}, {"id": 101, "char": "佃"}, {"id": 102, "char": "伺"}, {"id": 103, "char": "囱"}, {"id": 104, "char": "肛"}, {"id": 105, "char": "肘"}, {"id": 106, "char": "甸"}, {"id": 107, "char": "狈"}, {"id": 108, "char": "鸠"}, {"id": 109, "char": "彤"}, {"id": 110, "char": "灸"}, {"id": 111, "char": "刨"}, {"id": 112, "char": "庇"}, {"id": 113, "char": "吝"}, {"id": 114, "char": "庐"}, {"id": 115, "char": "闰"}, {"id": 116, "char": "兑"}, {"id": 117, "char": "灼"}, {"id": 118, "char": "沐"}, {"id": 119, "char": "沛"}, {"id": 120, "char": "汰"}, {"id": 121, "char": "沥"}, {"id": 122, "char": "沦"}, {"id": 123, "char": "汹"}, {"id": 124, "char": "沧"}, {"id": 125, "char": "沪"}, {"id": 126, "char": "忱"}, {"id": 127, "char": "诅"}, {"id": 128, "char": "诈"}, {"id": 129, "char": "罕"}, {"id": 130, "char": "屁"}, {"id": 131, "char": "坠"}, {"id": 132, "char": "妓"}, {"id": 133, "char": "姊"}, {"id": 134, "char": "妒"}, {"id": 135, "char": "纬"}, {"id": 136, "char": "玫"}, {"id": 137, "char": "卦"}, {"id": 138, "char": "坷"}, {"id": 139, "char": "坯"}, {"id": 140, "char": "拓"}, {"id": 141, "char": "坪"}, {"id": 142, "char": "坤"}, {"id": 143, "char": "拄"}, {"id": 144, "char": "拧"}, {"id": 145, "char": "拂"}, {"id": 146, "char": "拙"}, {"id": 147, "char": "拇"}, {"id": 148, "char": "拗"}, {"id": 149, "char": "茉"}, {"id": 150, "char": "昔"}, {"id": 151, "char": "苛"}, {"id": 152, "char": "苫"}, {"id": 153, "char": "苟"}, {"id": 154, "char": "苞"}, {"id": 155, "char": "茁"}, {"id": 156, "char": "苔"}, {"id": 157, "char": "枉"}, {"id": 158, "char": "枢"}, {"id": 159, "char": "枚"}, {"id": 160, "char": "枫"}, {"id": 161, "char": "杭"}, {"id": 162, "char": "郁"}, {"id": 163, "char": "矾"}, {"id": 164, "char": "奈"}, {"id": 165, "char": "奄"}, {"id": 166, "char": "殴"}, {"id": 167, "char": "歧"}, {"id": 168, "char": "卓"}, {"id": 169, "char": "昙"}, {"id": 170, "char": "哎"}, {"id": 171, "char": "咕"}, {"id": 172, "char": "呵"}, {"id": 173, "char": "咙"}, {"id": 174, "char": "呻"}, {"id": 175, "char": "咒"}, {"id": 176, "char": "咆"}, {"id": 177, "char": "咖"}, {"id": 178, "char": "帕"}, {"id": 179, "char": "账"}, {"id": 180, "char": "贬"}, {"id": 181, "char": "贮"}, {"id": 182, "char": "氛"}, {"id": 183, "char": "秉"}, {"id": 184, "char": "岳"}, {"id": 185, "char": "侠"}, {"id": 186, "char": "侥"}, {"id": 187, "char": "侣"}, {"id": 188, "char": "侈"}, {"id": 189, "char": "卑"}, {"id": 190, "char": "刽"}, {"id": 191, "char": "刹"}, {"id": 192, "char": "肴"}, {"id": 193, "char": "觅"}, {"id": 194, "char": "忿"}, {"id": 195, "char": "瓮"}, {"id": 196, "char": "肮"}, {"id": 197, "char": "肪"}, {"id": 198, "char": "狞"}, {"id": 199, "char": "庞"}, {"id": 200, "char": "疟"}, {"id": 201, "char": "疙"}, {"id": 202, "char": "疚"}, {"id": 203, "char": "卒"}, {"id": 204, "char": "氓"}, {"id": 205, "char": "炬"}, {"id": 206, "char": "沽"}, {"id": 207, "char": "沮"}, {"id": 208, "char": "泣"}, {"id": 209, "char": "泞"}, {"id": 210, "char": "泌"}, {"id": 211, "char": "沼"}, {"id": 212, "char": "怔"}, {"id": 213, "char": "怯"}, {"id": 214, "char": "宠"}, {"id": 215, "char": "宛"}, {"id": 216, "char": "衩"}, {"id": 217, "char": "祈"}, {"id": 218, "char": "诡"}, {"id": 219, "char": "帚"}, {"id": 220, "char": "屉"}, {"id": 221, "char": "弧"}, {"id": 222, "char": "弥"}, {"id": 223, "char": "陋"}, {"id": 224, "char": "陌"}, {"id": 225, "char": "函"}, {"id": 226, "char": "姆"}, {"id": 227, "char": "虱"}, {"id": 228, "char": "叁"}, {"id": 229, "char": "绅"}, {"id": 230, "char": "驹"}, {"id": 231, "char": "绊"}, {"id": 232, "char": "绎"}, {"id": 233, "char": "契"}, {"id": 234, "char": "贰"}, {"id": 235, "char": "玷"}, {"id": 236, "char": "玲"}, {"id": 237, "char": "珊"}, {"id": 238, "char": "拭"}, {"id": 239, "char": "拷"}, {"id": 240, "char": "拱"}, {"id": 241, "char": "挟"}, {"id": 242, "char": "垢"}, {"id": 243, "char": "垛"}, {"id": 244, "char": "拯"}, {"id": 245, "char": "荆"}, {"id": 246, "char": "茸"}, {"id": 247, "char": "茬"}, {"id": 248, "char": "荚"}, {"id": 249, "char": "茵"}, {"id": 250, "char": "茴"}, {"id": 251, "char": "荞"}, {"id": 252, "char": "荠"}, {"id": 253, "char": "荤"}, {"id": 254, "char": "荧"}, {"id": 255, "char": "荔"}, {"id": 256, "char": "栈"}, {"id": 257, "char": "柑"}, {"id": 258, "char": "栅"}, {"id": 259, "char": "柠"}, {"id": 260, "char": "枷"}, {"id": 261, "char": "勃"}, {"id": 262, "char": "柬"}, {"id": 263, "char": "砂"}, {"id": 264, "char": "泵"}, {"id": 265, "char": "砚"}, {"id": 266, "char": "鸥"}, {"id": 267, "char": "轴"}, {"id": 268, "char": "韭"}, {"id": 269, "char": "虐"}, {"id": 270, "char": "昧"}, {"id": 271, "char": "盹"}, {"id": 272, "char": "咧"}, {"id": 273, "char": "昵"}, {"id": 274, "char": "昭"}, {"id": 275, "char": "盅"}, {"id": 276, "char": "勋"}, {"id": 277, "char": "哆"}, {"id": 278, "char": "咪"}, {"id": 279, "char": "哟"}, {"id": 280, "char": "幽"}, {"id": 281, "char": "钙"}, {"id": 282, "char": "钝"}, {"id": 283, "char": "钠"}, {"id": 284, "char": "钦"}, {"id": 285, "char": "钧"}, {"id": 286, "char": "钮"}, {"id": 287, "char": "毡"}, {"id": 288, "char": "氢"}, {"id": 289, "char": "秕"}, {"id": 290, "char": "俏"}, {"id": 291, "char": "俄"}, {"id": 292, "char": "俐"}, {"id": 293, "char": "侯"}, {"id": 294, "char": "徊"}, {"id": 295, "char": "衍"}, {"id": 296, "char": "胚"}, {"id": 297, "char": "胧"}, {"id": 298, "char": "胎"}, {"id": 299, "char": "狰"}, {"id": 300, "char": "饵"}, {"id": 301, "char": "峦"}, {"id": 302, "char": "奕"}, {"id": 303, "char": "咨"}, {"id": 304, "char": "飒"}, {"id": 305, "char": "闺"}, {"id": 306, "char": "闽"}, {"id": 307, "char": "籽"}, {"id": 308, "char": "娄"}, {"id": 309, "char": "烁"}, {"id": 310, "char": "炫"}, {"id": 311, "char": "洼"}, {"id": 312, "char": "柒"}, {"id": 313, "char": "涎"}, {"id": 314, "char": "洛"}, {"id": 315, "char": "恃"}, {"id": 316, "char": "恍"}, {"id": 317, "char": "恬"}, {"id": 318, "char": "恤"}, {"id": 319, "char": "宦"}, {"id": 320, "char": "诫"}, {"id": 321, "char": "诬"}, {"id": 322, "char": "祠"}, {"id": 323, "char": "诲"}, {"id": 324, "char": "屏"}, {"id": 325, "char": "屎"}, {"id": 326, "char": "逊"}, {"id": 327, "char": "陨"}, {"id": 328, "char": "姚"}, {"id": 329, "char": "娜"}, {"id": 330, "char": "蚤"}, {"id": 331, "char": "骇"}, {"id": 332, "char": "耘"}, {"id": 333, "char": "耙"}, {"id": 334, "char": "秦"}, {"id": 335, "char": "匿"}, {"id": 336, "char": "埂"}, {"id": 337, "char": "捂"}, {"id": 338, "char": "捍"}, {"id": 339, "char": "袁"}, {"id": 340, "char": "捌"}, {"id": 341, "char": "挫"}, {"id": 342, "char": "挚"}, {"id": 343, "char": "捣"}, {"id": 344, "char": "捅"}, {"id": 345, "char": "埃"}, {"id": 346, "char": "耿"}, {"id": 347, "char": "聂"}, {"id": 348, "char": "荸"}, {"id": 349, "char": "莽"}, {"id": 350, "char": "莱"}, {"id": 351, "char": "莉"}, {"id": 352, "char": "莹"}, {"id": 353, "char": "莺"}, {"id": 354, "char": "梆"}, {"id": 355, "char": "栖"}, {"id": 356, "char": "桦"}, {"id": 357, "char": "栓"}, {"id": 358, "char": "桅"}, {"id": 359, "char": "桩"}, {"id": 360, "char": "贾"}, {"id": 361, "char": "酌"}, {"id": 362, "char": "砸"}, {"id": 363, "char": "砰"}, {"id": 364, "char": "砾"}, {"id": 365, "char": "殉"}, {"id": 366, "char": "逞"}, {"id": 367, "char": "哮"}, {"id": 368, "char": "唠"}, {"id": 369, "char": "哺"}, {"id": 370, "char": "剔"}, {"id": 371, "char": "蚌"}, {"id": 372, "char": "蚜"}, {"id": 373, "char": "畔"}, {"id": 374, "char": "蚣"}, {"id": 375, "char": "蚪"}, {"id": 376, "char": "蚓"}, {"id": 377, "char": "哩"}, {"id": 378, "char": "圃"}, {"id": 379, "char": "鸯"}, {"id": 380, "char": "唁"}, {"id": 381, "char": "哼"}, {"id": 382, "char": "唧"}, {"id": 383, "char": "唆"}, {"id": 384, "char": "峭"}, {"id": 385, "char": "峻"}, {"id": 386, "char": "赂"}, {"id": 387, "char": "赃"}, {"id": 388, "char": "钾"}, {"id": 389, "char": "铆"}, {"id": 390, "char": "氨"}, {"id": 391, "char": "秫"}, {"id": 392, "char": "笆"}, {"id": 393, "char": "俺"}, {"id": 394, "char": "赁"}, {"id": 395, "char": "倔"}, {"id": 396, "char": "殷"}, {"id": 397, "char": "耸"}, {"id": 398, "char": "舀"}, {"id": 399, "char": "豺"}, {"id": 400, "char": "豹"}, {"id": 401, "char": "颁"}, {"id": 402, "char": "胯"}, {"id": 403, "char": "胰"}, {"id": 404, "char": "脐"}, {"id": 405, "char": "脓"}, {"id": 406, "char": "逛"}, {"id": 407, "char": "卿"}, {"id": 408, "char": "鸵"}, {"id": 409, "char": "鸳"}, {"id": 410, "char": "馁"}, {"id": 411, "char": "凌"}, {"id": 412, "char": "凄"}, {"id": 413, "char": "衷"}, {"id": 414, "char": "郭"}, {"id": 415, "char": "斋"}, {"id": 416, "char": "疹"}, {"id": 417, "char": "紊"}, {"id": 418, "char": "瓷"}, {"id": 419, "char": "羔"}, {"id": 420, "char": "烙"}, {"id": 421, "char": "浦"}, {"id": 422, "char": "涡"}, {"id": 423, "char": "涣"}, {"id": 424, "char": "涤"}, {"id": 425, "char": "涧"}, {"id": 426, "char": "涕"}, {"id": 427, "char": "涩"}, {"id": 428, "char": "悍"}, {"id": 429, "char": "悯"}, {"id": 430, "char": "窍"}, {"id": 431, "char": "诺"}, {"id": 432, "char": "诽"}, {"id": 433, "char": "袒"}, {"id": 434, "char": "谆"}, {"id": 435, "char": "祟"}, {"id": 436, "char": "恕"}, {"id": 437, "char": "娩"}, {"id": 438, "char": "骏"}, {"id": 439, "char": "琐"}, {"id": 440, "char": "麸"}, {"id": 441, "char": "琉"}, {"id": 442, "char": "琅"}, {"id": 443, "char": "措"}, {"id": 444, "char": "捺"}, {"id": 445, "char": "捶"}, {"id": 446, "char": "赦"}, {"id": 447, "char": "埠"}, {"id": 448, "char": "捻"}, {"id": 449, "char": "掐"}, {"id": 450, "char": "掂"}, {"id": 451, "char": "掖"}, {"id": 452, "char": "掷"}, {"id": 453, "char": "掸"}, {"id": 454, "char": "掺"}, {"id": 455, "char": "勘"}, {"id": 456, "char": "聊"}, {"id": 457, "char": "娶"}, {"id": 458, "char": "菱"}, {"id": 459, "char": "菲"}, {"id": 460, "char": "萎"}, {"id": 461, "char": "菩"}, {"id": 462, "char": "萤"}, {"id": 463, "char": "乾"}, {"id": 464, "char": "萧"}, {"id": 465, "char": "萨"}, {"id": 466, "char": "菇"}, {"id": 467, "char": "彬"}, {"id": 468, "char": "梗"}, {"id": 469, "char": "梧"}, {"id": 470, "char": "梭"}, {"id": 471, "char": "曹"}, {"id": 472, "char": "酝"}, {"id": 473, "char": "酗"}, {"id": 474, "char": "厢"}, {"id": 475, "char": "硅"}, {"id": 476, "char": "硕"}, {"id": 477, "char": "奢"}, {"id": 478, "char": "盔"}, {"id": 479, "char": "匾"}, {"id": 480, "char": "颅"}, {"id": 481, "char": "彪"}, {"id": 482, "char": "眶"}, {"id": 483, "char": "晤"}, {"id": 484, "char": "曼"}, {"id": 485, "char": "晦"}, {"id": 486, "char": "冕"}, {"id": 487, "char": "啡"}, {"id": 488, "char": "畦"}, {"id": 489, "char": "趾"}, {"id": 490, "char": "啃"}, {"id": 491, "char": "蛆"}, {"id": 492, "char": "蚯"}, {"id": 493, "char": "蛉"}, {"id": 494, "char": "蛀"}, {"id": 495, "char": "唬"}, {"id": 496, "char": "啰"}, {"id": 497, "char": "唾"}, {"id": 498, "char": "啤"}, {"id": 499, "char": "啥"}, {"id": 500, "char": "啸"}, {"id": 501, "char": "崎"}, {"id": 502, "char": "逻"}, {"id": 503, "char": "崔"}, {"id": 504, "char": "崩"}, {"id": 505, "char": "婴"}, {"id": 506, "char": "赊"}, {"id": 507, "char": "铐"}, {"id": 508, "char": "铛"}, {"id": 509, "char": "铝"}, {"id": 510, "char": "铡"}, {"id": 511, "char": "铣"}, {"id": 512, "char": "铭"}, {"id": 513, "char": "矫"}, {"id": 514, "char": "秸"}, {"id": 515, "char": "秽"}, {"id": 516, "char": "笙"}, {"id": 517, "char": "笤"}, {"id": 518, "char": "偎"}, {"id": 519, "char": "傀"}, {"id": 520, "char": "躯"}, {"id": 521, "char": "兜"}, {"id": 522, "char": "衅"}, {"id": 523, "char": "徘"}, {"id": 524, "char": "徙"}, {"id": 525, "char": "舶"}, {"id": 526, "char": "舷"}, {"id": 527, "char": "舵"}, {"id": 528, "char": "敛"}, {"id": 529, "char": "翎"}, {"id": 530, "char": "脯"}, {"id": 531, "char": "逸"}, {"id": 532, "char": "凰"}, {"id": 533, "char": "猖"}, {"id": 534, "char": "祭"}, {"id": 535, "char": "烹"}, {"id": 536, "char": "庶"}, {"id": 537, "char": "庵"}, {"id": 538, "char": "痊"}, {"id": 539, "char": "阎"}, {"id": 540, "char": "阐"}, {"id": 541, "char": "眷"}, {"id": 542, "char": "焊"}, {"id": 543, "char": "焕"}, {"id": 544, "char": "鸿"}, {"id": 545, "char": "涯"}, {"id": 546, "char": "淑"}, {"id": 547, "char": "淌"}, {"id": 548, "char": "淮"}, {"id": 549, "char": "淆"}, {"id": 550, "char": "渊"}, {"id": 551, "char": "淫"}, {"id": 552, "char": "淳"}, {"id": 553, "char": "淤"}, {"id": 554, "char": "淀"}, {"id": 555, "char": "涮"}, {"id": 556, "char": "涵"}, {"id": 557, "char": "惦"}, {"id": 558, "char": "悴"}, {"id": 559, "char": "惋"}, {"id": 560, "char": "寂"}, {"id": 561, "char": "窒"}, {"id": 562, "char": "谍"}, {"id": 563, "char": "谐"}, {"id": 564, "char": "裆"}, {"id": 565, "char": "袱"}, {"id": 566, "char": "祷"}, {"id": 567, "char": "谒"}, {"id": 568, "char": "谓"}, {"id": 569, "char": "谚"}, {"id": 570, "char": "尉"}, {"id": 571, "char": "堕"}, {"id": 572, "char": "隅"}, {"id": 573, "char": "婉"}, {"id": 574, "char": "颇"}, {"id": 575, "char": "绰"}, {"id": 576, "char": "绷"}, {"id": 577, "char": "综"}, {"id": 578, "char": "绽"}, {"id": 579, "char": "缀"}, {"id": 580, "char": "巢"}, {"id": 581, "char": "琳"}, {"id": 582, "char": "琢"}, {"id": 583, "char": "琼"}, {"id": 584, "char": "揍"}, {"id": 585, "char": "堰"}, {"id": 586, "char": "揩"}, {"id": 587, "char": "揽"}, {"id": 588, "char": "揖"}, {"id": 589, "char": "彭"}, {"id": 590, "char": "揣"}, {"id": 591, "char": "搀"}, {"id": 592, "char": "搓"}, {"id": 593, "char": "壹"}, {"id": 594, "char": "搔"}, {"id": 595, "char": "葫"}, {"id": 596, "char": "募"}, {"id": 597, "char": "蒋"}, {"id": 598, "char": "蒂"}, {"id": 599, "char": "韩"}, {"id": 600, "char": "棱"}, {"id": 601, "char": "椰"}, {"id": 602, "char": "焚"}, {"id": 603, "char": "椎"}, {"id": 604, "char": "棺"}, {"id": 605, "char": "榔"}, {"id": 606, "char": "椭"}, {"id": 607, "char": "粟"}, {"id": 608, "char": "棘"}, {"id": 609, "char": "酣"}, {"id": 610, "char": "酥"}, {"id": 611, "char": "硝"}, {"id": 612, "char": "硫"}, {"id": 613, "char": "颊"}, {"id": 614, "char": "雳"}, {"id": 615, "char": "翘"}, {"id": 616, "char": "凿"}, {"id": 617, "char": "棠"}, {"id": 618, "char": "晰"}, {"id": 619, "char": "鼎"}, {"id": 620, "char": "喳"}, {"id": 621, "char": "遏"}, {"id": 622, "char": "晾"}, {"id": 623, "char": "畴"}, {"id": 624, "char": "跋"}, {"id": 625, "char": "跛"}, {"id": 626, "char": "蛔"}, {"id": 627, "char": "蜒"}, {"id": 628, "char": "蛤"}, {"id": 629, "char": "鹃"}, {"id": 630, "char": "喻"}, {"id": 631, "char": "啼"}, {"id": 632, "char": "喧"}, {"id": 633, "char": "嵌"}, {"id": 634, "char": "赋"}, {"id": 635, "char": "赎"}, {"id": 636, "char": "赐"}, {"id": 637, "char": "锉"}, {"id": 638, "char": "锌"}, {"id": 639, "char": "甥"}, {"id": 640, "char": "掰"}, {"id": 641, "char": "氮"}, {"id": 642, "char": "氯"}, {"id": 643, "char": "黍"}, {"id": 644, "char": "筏"}, {"id": 645, "char": "牍"}, {"id": 646, "char": "粤"}, {"id": 647, "char": "逾"}, {"id": 648, "char": "腌"}, {"id": 649, "char": "腋"}, {"id": 650, "char": "腕"}, {"id": 651, "char": "猩"}, {"id": 652, "char": "猬"}, {"id": 653, "char": "惫"}, {"id": 654, "char": "敦"}, {"id": 655, "char": "痘"}, {"id": 656, "char": "痢"}, {"id": 657, "char": "痪"}, {"id": 658, "char": "竣"}, {"id": 659, "char": "翔"}, {"id": 660, "char": "奠"}, {"id": 661, "char": "遂"}, {"id": 662, "char": "焙"}, {"id": 663, "char": "滞"}, {"id": 664, "char": "湘"}, {"id": 665, "char": "渤"}, {"id": 666, "char": "渺"}, {"id": 667, "char": "溃"}, {"id": 668, "char": "溅"}, {"id": 669, "char": "湃"}, {"id": 670, "char": "愕"}, {"id": 671, "char": "惶"}, {"id": 672, "char": "寓"}, {"id": 673, "char": "窖"}, {"id": 674, "char": "窘"}, {"id": 675, "char": "雇"}, {"id": 676, "char": "谤"}, {"id": 677, "char": "犀"}, {"id": 678, "char": "隘"}, {"id": 679, "char": "媒"}, {"id": 680, "char": "媚"}, {"id": 681, "char": "婿"}, {"id": 682, "char": "缅"}, {"id": 683, "char": "缆"}, {"id": 684, "char": "缔"}, {"id": 685, "char": "缕"}, {"id": 686, "char": "骚"}, {"id": 687, "char": "瑟"}, {"id": 688, "char": "鹉"}, {"id": 689, "char": "瑰"}, {"id": 690, "char": "搪"}, {"id": 691, "char": "聘"}, {"id": 692, "char": "斟"}, {"id": 693, "char": "靴"}, {"id": 694, "char": "靶"}, {"id": 695, "char": "蓖"}, {"id": 696, "char": "蒿"}, {"id": 697, "char": "蒲"}, {"id": 698, "char": "蓉"}, {"id": 699, "char": "楔"}, {"id": 700, "char": "椿"}, {"id": 701, "char": "楷"}, {"id": 702, "char": "榄"}, {"id": 703, "char": "楞"}, {"id": 704, "char": "楣"}, {"id": 705, "char": "酪"}, {"id": 706, "char": "碘"}, {"id": 707, "char": "硼"}, {"id": 708, "char": "碉"}, {"id": 709, "char": "辐"}, {"id": 710, "char": "辑"}, {"id": 711, "char": "频"}, {"id": 712, "char": "睹"}, {"id": 713, "char": "睦"}, {"id": 714, "char": "瞄"}, {"id": 715, "char": "嗜"}, {"id": 716, "char": "嗦"}, {"id": 717, "char": "暇"}, {"id": 718, "char": "畸"}, {"id": 719, "char": "跷"}, {"id": 720, "char": "跺"}, {"id": 721, "char": "蜈"}, {"id": 722, "char": "蜗"}, {"id": 723, "char": "蜕"}, {"id": 724, "char": "蛹"}, {"id": 725, "char": "嗅"}, {"id": 726, "char": "嗡"}, {"id": 727, "char": "嗤"}, {"id": 728, "char": "署"}, {"id": 729, "char": "蜀"}, {"id": 730, "char": "幌"}, {"id": 731, "char": "锚"}, {"id": 732, "char": "锥"}, {"id": 733, "char": "锨"}, {"id": 734, "char": "锭"}, {"id": 735, "char": "锰"}, {"id": 736, "char": "稚"}, {"id": 737, "char": "颓"}, {"id": 738, "char": "筷"}, {"id": 739, "char": "魁"}, {"id": 740, "char": "衙"}, {"id": 741, "char": "腻"}, {"id": 742, "char": "腮"}, {"id": 743, "char": "腺"}, {"id": 744, "char": "鹏"}, {"id": 745, "char": "肄"}, {"id": 746, "char": "猿"}, {"id": 747, "char": "颖"}, {"id": 748, "char": "煞"}, {"id": 749, "char": "雏"}, {"id": 750, "char": "馍"}, {"id": 751, "char": "馏"}, {"id": 752, "char": "禀"}, {"id": 753, "char": "痹"}, {"id": 754, "char": "廓"}, {"id": 755, "char": "痴"}, {"id": 756, "char": "靖"}, {"id": 757, "char": "誊"}, {"id": 758, "char": "漓"}, {"id": 759, "char": "溢"}, {"id": 760, "char": "溯"}, {"id": 761, "char": "溶"}, {"id": 762, "char": "滓"}, {"id": 763, "char": "溺"}, {"id": 764, "char": "寞"}, {"id": 765, "char": "窥"}, {"id": 766, "char": "窟"}, {"id": 767, "char": "寝"}, {"id": 768, "char": "褂"}, {"id": 769, "char": "裸"}, {"id": 770, "char": "谬"}, {"id": 771, "char": "媳"}, {"id": 772, "char": "嫉"}, {"id": 773, "char": "缚"}, {"id": 774, "char": "缤"}, {"id": 775, "char": "剿"}, {"id": 776, "char": "赘"}, {"id": 777, "char": "熬"}, {"id": 778, "char": "赫"}, {"id": 779, "char": "蔫"}, {"id": 780, "char": "摹"}, {"id": 781, "char": "蔓"}, {"id": 782, "char": "蔗"}, {"id": 783, "char": "蔼"}, {"id": 784, "char": "熙"}, {"id": 785, "char": "蔚"}, {"id": 786, "char": "兢"}, {"id": 787, "char": "榛"}, {"id": 788, "char": "榕"}, {"id": 789, "char": "酵"}, {"id": 790, "char": "碟"}, {"id": 791, "char": "碴"}, {"id": 792, "char": "碱"}, {"id": 793, "char": "碳"}, {"id": 794, "char": "辕"}, {"id": 795, "char": "辖"}, {"id": 796, "char": "雌"}, {"id": 797, "char": "墅"}, {"id": 798, "char": "嘁"}, {"id": 799, "char": "踊"}, {"id": 800, "char": "蝉"}, {"id": 801, "char": "嘀"}, {"id": 802, "char": "幔"}, {"id": 803, "char": "镀"}, {"id": 804, "char": "舔"}, {"id": 805, "char": "熏"}, {"id": 806, "char": "箍"}, {"id": 807, "char": "箕"}, {"id": 808, "char": "箫"}, {"id": 809, "char": "舆"}, {"id": 810, "char": "僧"}, {"id": 811, "char": "孵"}, {"id": 812, "char": "瘩"}, {"id": 813, "char": "瘟"}, {"id": 814, "char": "彰"}, {"id": 815, "char": "粹"}, {"id": 816, "char": "漱"}, {"id": 817, "char": "漩"}, {"id": 818, "char": "漾"}, {"id": 819, "char": "慷"}, {"id": 820, "char": "寡"}, {"id": 821, "char": "寥"}, {"id": 822, "char": "谭"}, {"id": 823, "char": "褐"}, {"id": 824, "char": "褪"}, {"id": 825, "char": "隧"}, {"id": 826, "char": "嫡"}, {"id": 827, "char": "缨"}, {"id": 828, "char": "撵"}, {"id": 829, "char": "撩"}, {"id": 830, "char": "撮"}, {"id": 831, "char": "撬"}, {"id": 832, "char": "擒"}, {"id": 833, "char": "墩"}, {"id": 834, "char": "撰"}, {"id": 835, "char": "鞍"}, {"id": 836, "char": "蕊"}, {"id": 837, "char": "蕴"}, {"id": 838, "char": "樊"}, {"id": 839, "char": "樟"}, {"id": 840, "char": "橄"}, {"id": 841, "char": "敷"}, {"id": 842, "char": "豌"}, {"id": 843, "char": "醇"}, {"id": 844, "char": "磕"}, {"id": 845, "char": "磅"}, {"id": 846, "char": "碾"}, {"id": 847, "char": "嘶"}, {"id": 848, "char": "嘲"}, {"id": 849, "char": "嘹"}, {"id": 850, "char": "蝠"}, {"id": 851, "char": "蝎"}, {"id": 852, "char": "蝌"}, {"id": 853, "char": "蝗"}, {"id": 854, "char": "蝙"}, {"id": 855, "char": "嘿"}, {"id": 856, "char": "幢"}, {"id": 857, "char": "镊"}, {"id": 858, "char": "镐"}, {"id": 859, "char": "稽"}, {"id": 860, "char": "篓"}, {"id": 861, "char": "膘"}, {"id": 862, "char": "鲤"}, {"id": 863, "char": "鲫"}, {"id": 864, "char": "褒"}, {"id": 865, "char": "瘪"}, {"id": 866, "char": "瘤"}, {"id": 867, "char": "瘫"}, {"id": 868, "char": "凛"}, {"id": 869, "char": "憋"}, {"id": 870, "char": "澎"}, {"id": 871, "char": "潭"}, {"id": 872, "char": "潦"}, {"id": 873, "char": "澳"}, {"id": 874, "char": "潘"}, {"id": 875, "char": "澈"}, {"id": 876, "char": "澜"}, {"id": 877, "char": "澄"}, {"id": 878, "char": "憔"}, {"id": 879, "char": "懊"}, {"id": 880, "char": "憎"}, {"id": 881, "char": "翩"}, {"id": 882, "char": "褥"}, {"id": 883, "char": "谴"}, {"id": 884, "char": "鹤"}, {"id": 885, "char": "憨"}, {"id": 886, "char": "履"}, {"id": 887, "char": "嬉"}, {"id": 888, "char": "豫"}, {"id": 889, "char": "缭"}, {"id": 890, "char": "撼"}, {"id": 891, "char": "擂"}, {"id": 892, "char": "擅"}, {"id": 893, "char": "蕾"}, {"id": 894, "char": "薛"}, {"id": 895, "char": "薇"}, {"id": 896, "char": "擎"}, {"id": 897, "char": "翰"}, {"id": 898, "char": "噩"}, {"id": 899, "char": "橱"}, {"id": 900, "char": "橙"}, {"id": 901, "char": "瓢"}, {"id": 902, "char": "磺"}, {"id": 903, "char": "霍"}, {"id": 904, "char": "霎"}, {"id": 905, "char": "辙"}, {"id": 906, "char": "冀"}, {"id": 907, "char": "踱"}, {"id": 908, "char": "蹂"}, {"id": 909, "char": "蟆"}, {"id": 910, "char": "螃"}, {"id": 911, "char": "螟"}, {"id": 912, "char": "噪"}, {"id": 913, "char": "鹦"}, {"id": 914, "char": "黔"}, {"id": 915, "char": "穆"}, {"id": 916, "char": "篡"}, {"id": 917, "char": "篷"}, {"id": 918, "char": "篙"}, {"id": 919, "char": "篱"}, {"id": 920, "char": "儒"}, {"id": 921, "char": "膳"}, {"id": 922, "char": "鲸"}, {"id": 923, "char": "瘾"}, {"id": 924, "char": "瘸"}, {"id": 925, "char": "糙"}, {"id": 926, "char": "燎"}, {"id": 927, "char": "濒"}, {"id": 928, "char": "憾"}, {"id": 929, "char": "懈"}, {"id": 930, "char": "窿"}, {"id": 931, "char": "缰"}, {"id": 932, "char": "壕"}, {"id": 933, "char": "藐"}, {"id": 934, "char": "檬"}, {"id": 935, "char": "檐"}, {"id": 936, "char": "檩"}, {"id": 937, "char": "檀"}, {"id": 938, "char": "礁"}, {"id": 939, "char": "磷"}, {"id": 940, "char": "瞭"}, {"id": 941, "char": "瞬"}, {"id": 942, "char": "瞳"}, {"id": 943, "char": "瞪"}, {"id": 944, "char": "曙"}, {"id": 945, "char": "蹋"}, {"id": 946, "char": "蟋"}, {"id": 947, "char": "蟀"}, {"id": 948, "char": "嚎"}, {"id": 949, "char": "赡"}, {"id": 950, "char": "镣"}, {"id": 951, "char": "魏"}, {"id": 952, "char": "簇"}, {"id": 953, "char": "儡"}, {"id": 954, "char": "徽"}, {"id": 955, "char": "爵"}, {"id": 956, "char": "朦"}, {"id": 957, "char": "臊"}, {"id": 958, "char": "鳄"}, {"id": 959, "char": "糜"}, {"id": 960, "char": "癌"}, {"id": 961, "char": "懦"}, {"id": 962, "char": "豁"}, {"id": 963, "char": "臀"}, {"id": 964, "char": "藕"}, {"id": 965, "char": "藤"}, {"id": 966, "char": "瞻"}, {"id": 967, "char": "嚣"}, {"id": 968, "char": "鳍"}, {"id": 969, "char": "癞"}, {"id": 970, "char": "瀑"}, {"id": 971, "char": "襟"}, {"id": 972, "char": "璧"}, {"id": 973, "char": "戳"}, {"id": 974, "char": "攒"}, {"id": 975, "char": "孽"}, {"id": 976, "char": "蘑"}, {"id": 977, "char": "藻"}, {"id": 978, "char": "蹭"}, {"id": 979, "char": "蹬"}, {"id": 980, "char": "簸"}, {"id": 981, "char": "簿"}, {"id": 982, "char": "蟹"}, {"id": 983, "char": "靡"}, {"id": 984, "char": "癣"}, {"id": 985, "char": "羹"}, {"id": 986, "char": "鳖"}, {"id": 987, "char": "鬓"}, {"id": 988, "char": "攘"}, {"id": 989, "char": "蠕"}, {"id": 990, "char": "巍"}, {"id": 991, "char": "鳞"}, {"id": 992, "char": "糯"}, {"id": 993, "char": "譬"}, {"id": 994, "char": "霹"}, {"id": 995, "char": "躏"}, {"id": 996, "char": "髓"}, {"id": 997, "char": "蘸"}, {"id": 998, "char": "镶"}, {"id": 999, "char": "瓤"}, {"id": 1000, "char": "矗"}]